connect/eaas/dataclasses.py
connect/eaas/extension.py
connect/eaas/runner/__init__.py
connect/eaas/runner/artworks/__init__.py
connect/eaas/runner/artworks/ansi_regular.flf
connect/eaas/runner/artworks/banner.py
connect/eaas/runner/artworks/bloody.flf
connect/eaas/runner/config.py
connect/eaas/runner/constants.py
connect/eaas/runner/exceptions.py
connect/eaas/runner/handlers/__init__.py
connect/eaas/runner/handlers/anvil.py
connect/eaas/runner/handlers/base.py
connect/eaas/runner/handlers/events.py
connect/eaas/runner/handlers/transformations.py
connect/eaas/runner/handlers/web.py
connect/eaas/runner/helpers.py
connect/eaas/runner/logging.py
connect/eaas/runner/main.py
connect/eaas/runner/managers/__init__.py
connect/eaas/runner/managers/background.py
connect/eaas/runner/managers/base.py
connect/eaas/runner/managers/interactive.py
connect/eaas/runner/managers/scheduled.py
connect/eaas/runner/managers/transformation.py
connect/eaas/runner/master.py
connect/eaas/runner/workers/__init__.py
connect/eaas/runner/workers/anvil.py
connect/eaas/runner/workers/base.py
connect/eaas/runner/workers/events.py
connect/eaas/runner/workers/transformations.py
connect/eaas/runner/workers/web.py
connect_extension_runner-37.0.dist-info/LICENSE
connect_extension_runner-37.0.dist-info/METADATA
connect_extension_runner-37.0.dist-info/WHEEL
connect_extension_runner-37.0.dist-info/entry_points.txt
connect_extension_runner-37.0.dist-info/RECORD
