Metadata-Version: 2.3
Name: connect-extension-runner
Version: 37.0
Summary: CloudBlue Connect EaaS Extension Runner
License: Apache-2.0
Author: CloudBlue LLC
Requires-Python: >=3.9,<4
Classifier: Development Status :: 5 - Production/Stable
Classifier: Environment :: Console
Classifier: Intended Audience :: Developers
Classifier: License :: OSI Approved :: Apache Software License
Classifier: Operating System :: OS Independent
Classifier: Programming Language :: Python :: 3
Classifier: Programming Language :: Python :: 3.9
Classifier: Programming Language :: Python :: 3.10
Classifier: Programming Language :: Python :: 3.11
Classifier: Programming Language :: Python :: 3.12
Classifier: Programming Language :: Python :: 3.13
Classifier: Topic :: Software Development :: Libraries
Classifier: Topic :: Utilities
Requires-Dist: backoff (>=2.2.1,<3.0.0)
Requires-Dist: connect-eaas-core (>=33.0,<38)
Requires-Dist: connect-openapi-client (>=29.0,<38)
Requires-Dist: devtools (>=0.12.2,<0.13.0)
Requires-Dist: httpx (>=0.23,<0.29)
Requires-Dist: logzio-python-handler (>=4.1.4,<5.0.0)
Requires-Dist: lxml (>=5.4.0,<6.0.0)
Requires-Dist: openpyxl (>=3.0.0,<4)
Requires-Dist: pyfiglet (>=1.0.2,<2.0.0)
Requires-Dist: python-socks[asyncio] (>=2.5.1,<3.0.0)
Requires-Dist: rich (>=12)
Requires-Dist: uvloop (>=0.21,<0.22)
Requires-Dist: watchfiles (>=1.0.5,<2.0.0)
Requires-Dist: websockets (==13.*)
Project-URL: Homepage, https://connect.cloudblue.com
Project-URL: Repository, https://github.com/cloudblue/connect-extension-runner
